{"chunk_definitions":[{"row":7,"row_count":1,"visible":true,"expansion_state":0,"options":{"engine":"r","label":"setup","include":false},"document_id":"2960AF43","chunk_id":"csetup_chunk","chunk_label":"setup"},{"row":28,"row_count":1,"visible":true,"expansion_state":0,"options":{"engine":"r","include":false,"label":"unnamed-chunk-2"},"document_id":"2960AF43","chunk_id":"c1re43prsc00a","chunk_label":"unnamed-chunk-1"},{"row":85,"row_count":1,"visible":true,"expansion_state":0,"options":{"engine":"r","label":"unnamed-chunk-5"},"document_id":"2960AF43","chunk_id":"csuf05trk421j","chunk_label":"unnamed-chunk-2"},{"row":103,"row_count":1,"visible":true,"expansion_state":0,"options":{"engine":"r","label":"unnamed-chunk-7"},"document_id":"2960AF43","chunk_id":"c3dkc7aikvgm9","chunk_label":"unnamed-chunk-4"},{"row":125,"row_count":1,"visible":true,"expansion_state":0,"options":{"engine":"r","label":"unnamed-chunk-23"},"document_id":"2960AF43","chunk_id":"c0zrayfqo6ca9","chunk_label":"unnamed-chunk-7"}],"doc_write_time":1694013076,"working_dir":null,"default_chunk_options":{"echo":false,"warning":false,"message":false}}